checkipaconsistency/__init__.py
checkipaconsistency/__main__.py
checkipaconsistency/__version__.py
checkipaconsistency/freeipaserver.py
checkipaconsistency/main.py
checkipaconsistency-2.7.10.dist-info/LICENSE.txt
checkipaconsistency-2.7.10.dist-info/METADATA
checkipaconsistency-2.7.10.dist-info/WHEEL
checkipaconsistency-2.7.10.dist-info/entry_points.txt
checkipaconsistency-2.7.10.dist-info/top_level.txt
checkipaconsistency-2.7.10.dist-info/RECORD
