Metadata-Version: 2.1
Name: checkipaconsistency
Version: 2.7.10
Summary: Tool to check consistency across FreeIPA servers
Home-page: https://github.com/peterpakos/checkipaconsistency
Author: Peter Pakos
Author-email: peter.pakos@wandisco.com
License: GPLv3
Keywords: freeipa ipa ldap consistency cipa
Platform: UNKNOWN
Classifier: Programming Language :: Python :: 2
Classifier: Programming Language :: Python :: 2.7
Classifier: Programming Language :: Python :: 3
Classifier: Programming Language :: Python :: 3.4
Classifier: Programming Language :: Python :: 3.5
Classifier: Programming Language :: Python :: 3.6
Classifier: License :: OSI Approved :: GNU General Public License v3 (GPLv3)
Classifier: Topic :: System :: Systems Administration :: Authentication/Directory :: LDAP
Requires-Dist: pplogger
Requires-Dist: python-ldap
Requires-Dist: prettytable
Requires-Dist: dnspython
